[
  {
    "year": "2016",
    "month": [
      {
        "title" : "янв"
      },
      {
        "title" : "фев"
      },
      {
        "title" : "март"
      },
      {
        "title" : "апр"
      },
      {
        "title" : "май"
      },
      {
        "title" : "июнь"
      },
      {
        "title" : "июль"
      },
      {
        "title" : "авг"
      },
      {
        "title" : "сент"
      },
      {
        "title" : "окт"
      },
      {
        "title" : "нояб"
      },
      {
        "title" : "дек"
      }
    ]
  },
  {
    "year": "2017",
    "month": [
      {
        "title" : "янв"
      },
      {
        "title" : "фев"
      },
      {
        "title" : "март"
      },
      {
        "title" : "апр"
      },
      {
        "title" : "май",
        "days" : [
          {
            "title" : "2 мая",
            "text" : "Первый репортаж со стройки",
            "img" : "./static/img/gk/gk_new-quality-1.jpg"
          },
          {
            "title" : "3 мая",
            "text" : "Второй репортаж со стройки",
            "img" : "./static/img/gk/gk_new-quality-2.jpg"
          }
        ]
      },
      {
        "title" : "июнь"
      },
      {
        "title" : "июль"
      },
      {
        "title" : "авг"
      },
      {
        "title" : "сент"
      },
      {
        "title" : "окт"
      },
      {
        "title" : "нояб"
      },
      {
        "title" : "дек"
      }
    ]
  },

  {
    "year": "2018",
    "month": [
      {
        "title" : "янв",
        "caption_actual" : "2.00%",
        "caption_planned": "1.60%",
        "days" : [
          {
            "title" : "2 мая",
            "text" : "Первый репортаж со стройки",
            "img" : "./static/img/gk/gk_new-quality-1.jpg"
          },
          {
            "title" : "3 мая",
            "text" : "Второй репортаж со стройки",
            "img" : "./static/img/gk/gk_new-quality-2.jpg"
          }
        ]
      },
      {
        "title" : "фев",
        "caption_actual" : "3.25%",
        "caption_planned": "6.1%",
        "days" : [
          {
            "title" : "2 мая",
            "text" : "Первый репортаж со стройки",
            "img" : "./static/img/gk/gk_new-quality-1.jpg"
          },
          {
            "title" : "3 мая",
            "text" : "Второй репортаж со стройки",
            "img" : "./static/img/gk/gk_new-quality-2.jpg"
          }
        ]
      },
      {
        "title" : "март",
        "caption_actual" : "3.70%",
        "caption_planned": "2.30%",
        "days" : [
          {
            "title" : "2 марта",
            "text" : "Первый репортаж со стройки ",
            "img" : "./static/img/gk/gk_new-quality-1.jpg"
          },
          {
            "title" : "3 марта",
            "text" : "Второй репортаж со стройки",
            "img" : "./static/img/gk/gk_new-quality-2.jpg"
          }
        ]
      },
      {
        "title" : "апр",
        "caption_actual" : "6.20%",
        "caption_planned": "4.50%",
        "days" : [
          {
            "title" : "2 мая",
            "text" : "Первый репортаж со стройки",
            "img" : "./static/img/gk/gk_new-quality-1.jpg"
          },
          {
            "title" : "3 мая",
            "text" : "Второй репортаж со стройки",
            "img" : "./static/img/gk/gk_new-quality-2.jpg"
          }
        ]
      },
      {
        "title" : "май",
        "caption_actual" : "8.50%",
        "caption_planned": "5.60%",
        "days" : [
          {
            "title" : "2 мая",
            "text" : "Первый репортаж со стройки",
            "img" : "./static/img/gk/gk_new-quality-1.jpg"
          },
          {
            "title" : "3 мая",
            "text" : "Второй репортаж со стройки",
            "img" : "./static/img/gk/gk_new-quality-2.jpg"
          }
        ]
      },
      {
        "title" : "июнь",
        "caption_actual" : "9.90%",
        "caption_planned": "6.10%",
        "days" : [
          {
            "title" : "2 мая",
            "text" : "Первый репортаж со стройки",
            "img" : "./static/img/gk/gk_new-quality-1.jpg"
          },
          {
            "title" : "3 мая",
            "text" : "Второй репортаж со стройки",
            "img" : "./static/img/gk/gk_new-quality-2.jpg"
          }
        ]
      },
      {
        "title" : "июль",
        "caption_actual" : "12.30%",
        "caption_planned": "9.90%",
        "days" : [
          {
            "title" : "2 мая",
            "text" : "Первый репортаж со стройки",
            "img" : "./static/img/gk/gk_new-quality-1.jpg"
          },
          {
            "title" : "3 мая",
            "text" : "Второй репортаж со стройки",
            "img" : "./static/img/gk/gk_new-quality-2.jpg"
          }
        ]
      },
      {
        "title" : "август 2018",
        "subtitle" : "строительство идет по плану",
        "caption_actual" : "12.30%",
        "caption_planned": "9.90%",
        "days" : [
          {
            "title" : "2 августа",
            "text" : "В секции 1 идет монтаж внутренних инженерных сетей, витражных алюминиевых и оконных ПВХ конструкций, дверей алюминиевых, квартирных, противопожарных. Ведутся работы по отделке наружного фасада и устройства кровли. Проводятся внутренние отделочные работы. Идёт монтаж лифтов. Ведется благоустройство территории. В секции 2 идет устройство кровли. Ведется благоустройство территории. В секции 3 идет устройство монолитных стен и пилонов 15-го этажа. Ведутся работы по кирпичной кладке стен и перегородок 7-го этажа. Ведется монтаж внутренних инженерных сетей и монтаж наружных сетей. В секции 4 идет устройство монолитного каркаса ниже нуля. В секции 5 идет устройство монолитных стен и пилонов 15-го этажа. Ведутся работы по кирпичной кладке стен и перегородок 8-го этажа. Ведется монтаж внутренних инженерных сетей и монтаж наружных сетей. Ежедневно на строительстве Литера 6 трудятся более 190 специалистов и 29 единиц механической техники. Еще больше фотографий в фотоальбоме https://vk.com/album-105401701_257373261.",
            "img" : "./static/img/gk/gk_new-quality-1.jpg"
          },
          {
            "title" : "3 августа",
            "text" : "Второй репортаж со стройки",
            "img" : "./static/img/gk/gk_new-quality-2.jpg"
          },
          {
            "title" : "15 августа",
            "text" : "Закончено утепление фасада, рабочие готовят поверхность к окраске.",
            "img" : "./static/img/gk/gk_new-quality-3.jpg"
          },
          {
            "title" : "25 августа",
            "text" : "Закончено утепление фасада, рабочие готовят поверхность к окраске.",
            "img" : "./static/img/gk/gk_new-quality-4.jpg"
          },
          {
            "title" : "30 августа",
            "text" : "Закончено утепление фасада, рабочие готовят поверхность к окраске.",
            "img" : "./static/img/gk/gk_new-quality-5.jpg"
          },
          {
            "title" : "1 августа",
            "text" : "Закончено утепление фасада, рабочие готовят поверхность к окраске.",
            "img" : "./static/img/gk/gk_new-quality-1.jpg"
          },
          {
            "title" : "4 августа",
            "text" : "Закончено утепление фасада, рабочие готовят поверхность к окраске.",
            "img" : "./static/img/gk/gk_new-quality-2.jpg"
          },
          {
            "title" : "1 августа",
            "text" : "Закончено утепление фасада, рабочие готовят поверхность к окраске.",
            "img" : "./static/img/gk/gk_new-quality-3.jpg"
          },
          {
            "title" : "8 августа",
            "text" : "Закончено утепление фасада, рабочие готовят поверхность к окраске.",
            "img" : "./static/img/gk/gk_new-quality-4.jpg"
          },
          {
            "title" : "1 августа",
            "text" : "Закончено утепление фасада, рабочие готовят поверхность к окраске.",
            "img" : "./static/img/gk/gk_new-quality-5.jpg"
          },
          {
            "title" : "2 августа",
            "text" : "Закончено утепление фасада, рабочие готовят поверхность к окраске.",
            "img" : "./static/img/gk/gk_new-quality-1.jpg"
          },
          {
            "title" : "6 августа",
            "text" : "Закончено утепление фасада, рабочие готовят поверхность к окраске.",
            "img" : "./static/img/gk/gk_new-quality-2.jpg"
          },
          {
            "title" : "11 августа",
            "text" : "Закончено утепление фасада, рабочие готовят поверхность к окраске.",
            "img" : "./static/img/gk/gk_new-quality-3.jpg"
          },
          {
            "title" : "3 августа",
            "text" : "Закончено утепление фасада, рабочие готовят поверхность к окраске.",
            "img" : "./static/img/gk/gk_new-quality-4.jpg"
          },
          {
            "title" : "4 августа",
            "text" : "Закончено утепление фасада, рабочие готовят поверхность к окраске.",
            "img" : "./static/img/gk/gk_new-quality-5.jpg"
          }
        ]
      },
      null,
      null,
      null,
      {
        "title" : "декабрь 2018",
        "subtitle" : "сдача"
      }
    ]
  }
]
