[
  {
    "year": "2016",
    "month": [
      {
        "title" : "янв"
      },
      {
        "title" : "фев"
      },
      {
        "title" : "март"
      },
      {
        "title" : "апр"
      },
      {
        "title" : "май"
      },
      {
        "title" : "июнь"
      },
      {
        "title" : "июль"
      },
      {
        "title" : "авг"
      },
      {
        "title" : "сент"
      },
      {
        "title" : "окт"
      },
      {
        "title" : "нояб"
      },
      {
        "title" : "дек"
      }
    ]
  },
  {
    "year": "2017",
    "month": [
      {
        "title" : "янв"
      },
      {
        "title" : "фев"
      },
      {
        "title" : "март"
      },
      {
        "title" : "апр"
      },
      {
        "title" : "май",
        "days" : [
          {
            "title" : "2 мая",
            "text" : "Первый репортаж со стройки",
            "img" : "./static/img/gk/gk_new-quality-1.jpg"
          },
          {
            "title" : "3 мая",
            "text" : "Второй репортаж со стройки",
            "img" : "./static/img/gk/gk_new-quality-2.jpg"
          }
        ]
      },
      {
        "title" : "июнь"
      },
      {
        "title" : "июль"
      },
      {
        "title" : "авг"
      },
      {
        "title" : "сент"
      },
      {
        "title" : "окт"
      },
      {
        "title" : "нояб"
      },
      {
        "title" : "дек"
      }
    ]
  },
  {
    "year": "2018",
    "month": [
      {
        "title" : "янв"
      },
      {
        "title" : "фев"
      },
      {
        "title" : "март",
        "days" : [
          {
            "title" : "2 марта",
            "text" : "Первый репортаж со стройки",
            "img" : "./static/img/gk/gk_new-quality-1.jpg"
          },
          {
            "title" : "3 марта",
            "text" : "Второй репортаж со стройки",
            "img" : "./static/img/gk/gk_new-quality-2.jpg"
          }
        ]
      },
      {
        "title" : "апр"
      },
      {
        "title" : "май"
      },
      {
        "title" : "июнь"
      },
      {
        "title" : "июль"
      },
      {
        "title" : "август 2018",
        "subtitle" : "строительство идет по плану",
        "caption" : "130%",
        "days" : [
          {
            "title" : "2 августа",
            "text" : "Первый репортаж со стройки",
            "img" : "./static/img/gk/gk_new-quality-1.jpg"
          },
          {
            "title" : "3 августа",
            "text" : "Второй репортаж со стройки",
            "img" : "./static/img/gk/gk_new-quality-2.jpg"
          },
          {
            "title" : "15 августа",
            "text" : "Закончено утепление фасада, рабочие готовят поверхность к окраске.",
            "img" : "./static/img/gk/gk_new-quality-3.jpg"
          },
          {
            "title" : "25 августа",
            "text" : "Закончено утепление фасада, рабочие готовят поверхность к окраске.",
            "img" : "./static/img/gk/gk_new-quality-4.jpg"
          },
          {
            "title" : "30 августа",
            "text" : "Закончено утепление фасада, рабочие готовят поверхность к окраске.",
            "img" : "./static/img/gk/gk_new-quality-5.jpg"
          },
          {
            "title" : "1 августа",
            "text" : "Закончено утепление фасада, рабочие готовят поверхность к окраске.",
            "img" : "./static/img/gk/gk_new-quality-5.jpg"
          },
          {
            "title" : "4 августа",
            "text" : "Закончено утепление фасада, рабочие готовят поверхность к окраске.",
            "img" : "./static/img/gk/gk_new-quality-5.jpg"
          },
          {
            "title" : "1 августа",
            "text" : "Закончено утепление фасада, рабочие готовят поверхность к окраске.",
            "img" : "./static/img/gk/gk_new-quality-5.jpg"
          },
          {
            "title" : "8 августа",
            "text" : "Закончено утепление фасада, рабочие готовят поверхность к окраске.",
            "img" : "./static/img/gk/gk_new-quality-5.jpg"
          },
          {
            "title" : "1 августа",
            "text" : "Закончено утепление фасада, рабочие готовят поверхность к окраске.",
            "img" : "./static/img/gk/gk_new-quality-5.jpg"
          },
          {
            "title" : "2 августа",
            "text" : "Закончено утепление фасада, рабочие готовят поверхность к окраске.",
            "img" : "./static/img/gk/gk_new-quality-5.jpg"
          },
          {
            "title" : "6 августа",
            "text" : "Закончено утепление фасада, рабочие готовят поверхность к окраске.",
            "img" : "./static/img/gk/gk_new-quality-5.jpg"
          },
          {
            "title" : "11 августа",
            "text" : "Закончено утепление фасада, рабочие готовят поверхность к окраске.",
            "img" : "./static/img/gk/gk_new-quality-5.jpg"
          },
          {
            "title" : "3 августа",
            "text" : "Закончено утепление фасада, рабочие готовят поверхность к окраске.",
            "img" : "./static/img/gk/gk_new-quality-5.jpg"
          },
          {
            "title" : "4 августа",
            "text" : "Закончено утепление фасада, рабочие готовят поверхность к окраске.",
            "img" : "./static/img/gk/gk_new-quality-5.jpg"
          }
        ]
      },
      null,
      null,
      null,
      {
        "title" : "декабрь 2018",
        "subtitle" : "сдача"
      }
    ]
  }
]
